nebula_gcp/__init__.py
nebula_gcp/_version.py
nebula_gcp/aiplatform.py
nebula_gcp/bigquery.py
nebula_gcp/cloud_run.py
nebula_gcp/cloud_storage.py
nebula_gcp/credentials.py
nebula_gcp/secret_manager.py
nebula_gcp/utilities.py
nebula_gcp/deployments/__init__.py
nebula_gcp/deployments/steps.py
nebula_gcp/models/__init__.py
nebula_gcp/models/cloud_run_v2.py
nebula_gcp/workers/__init__.py
nebula_gcp/workers/cloud_run.py
nebula_gcp/workers/cloud_run_v2.py
nebula_gcp/workers/vertex.py
nebula_gcp-1.0.0.dist-info/LICENSE
nebula_gcp-1.0.0.dist-info/METADATA
nebula_gcp-1.0.0.dist-info/WHEEL
nebula_gcp-1.0.0.dist-info/entry_points.txt
nebula_gcp-1.0.0.dist-info/top_level.txt
nebula_gcp-1.0.0.dist-info/RECORD
