Metadata-Version: 2.1
Name: nebula-gcp
Version: 1.0.0
Summary: Nebula tasks and subflows for interacting with Google Cloud Platform.
Home-page: https://github.com/kozmoai/nebula-gcp
Author: Kozmoai, Inc.
Author-email: help@kozmoai.org
License: Apache License 2.0
Keywords: nebula
Classifier: Natural Language :: English
Classifier: Intended Audience :: Developers
Classifier: Intended Audience :: System Administrators
Classifier: License :: OSI Approved :: Apache Software License
Classifier: Programming Language :: Python :: 3 :: Only
Classifier: Programming Language :: Python :: 3.7
Classifier: Programming Language :: Python :: 3.8
Classifier: Programming Language :: Python :: 3.9
Classifier: Programming Language :: Python :: 3.10
Classifier: Topic :: Software Development :: Libraries
Requires-Python: >=3.7
License-File: LICENSE
Requires-Dist: nebulaconsole
Requires-Dist: google-api-python-client >=2.20.0
Requires-Dist: google-cloud-storage >=2.0.0
Requires-Dist: tenacity >=8.0.0
Requires-Dist: python-slugify >=8.0.0
Provides-Extra: aiplatform
Requires-Dist: google-cloud-aiplatform ; extra == 'aiplatform'
Provides-Extra: all_extras
Requires-Dist: google-cloud-aiplatform ; extra == 'all_extras'
Requires-Dist: google-cloud-bigquery ; extra == 'all_extras'
Requires-Dist: google-cloud-bigquery-storage ; extra == 'all_extras'
Requires-Dist: google-cloud-secret-manager ; extra == 'all_extras'
Requires-Dist: google-cloud-storage ; extra == 'all_extras'
Provides-Extra: bigquery
Requires-Dist: google-cloud-bigquery ; extra == 'bigquery'
Requires-Dist: google-cloud-bigquery-storage ; extra == 'bigquery'
Provides-Extra: cloud_storage
Requires-Dist: google-cloud-storage ; extra == 'cloud_storage'
Provides-Extra: dev
Requires-Dist: black ; extra == 'dev'
Requires-Dist: coverage ; extra == 'dev'
Requires-Dist: flake8 ; extra == 'dev'
Requires-Dist: interrogate ; extra == 'dev'
Requires-Dist: isort ; extra == 'dev'
Requires-Dist: mkdocs ; extra == 'dev'
Requires-Dist: mkdocs-gen-files ; extra == 'dev'
Requires-Dist: mkdocs-material ; extra == 'dev'
Requires-Dist: mkdocstrings[python] ; extra == 'dev'
Requires-Dist: mypy ; extra == 'dev'
Requires-Dist: pandas ; extra == 'dev'
Requires-Dist: pillow ; extra == 'dev'
Requires-Dist: pre-commit ; extra == 'dev'
Requires-Dist: pyarrow ; extra == 'dev'
Requires-Dist: pytest ; extra == 'dev'
Requires-Dist: pytest-asyncio ; extra == 'dev'
Requires-Dist: pytest-cov ; extra == 'dev'
Requires-Dist: pytest-xdist ; extra == 'dev'
Requires-Dist: google-cloud-aiplatform ; extra == 'dev'
Requires-Dist: google-cloud-bigquery ; extra == 'dev'
Requires-Dist: google-cloud-bigquery-storage ; extra == 'dev'
Requires-Dist: google-cloud-secret-manager ; extra == 'dev'
Requires-Dist: google-cloud-storage ; extra == 'dev'
Requires-Dist: mock ; (python_version < "3.8") and extra == 'dev'
Provides-Extra: secret_manager
Requires-Dist: google-cloud-secret-manager ; extra == 'secret_manager'
